auto_sklearn2/__init__.py
auto_sklearn2/classifier.py
auto_sklearn2/regressor.py
auto_sklearn2-0.1.1.dist-info/METADATA
auto_sklearn2-0.1.1.dist-info/WHEEL
auto_sklearn2-0.1.1.dist-info/top_level.txt
auto_sklearn2-0.1.1.dist-info/RECORD
