Metadata-Version: 2.4
Name: auto-sklearn2
Version: 0.1.1
Summary: Python 3.13 compatible version of auto-sklearn
Home-page: https://github.com/agnelvishal/auto_sklearn2
Author: Agnel Vishal
Author-email: agnelvishal@gmail.com
Keywords: machine learning,auto-ml,automated machine learning,python 3.13
Classifier: Development Status :: 4 - Beta
Classifier: Intended Audience :: Science/Research
Classifier: Intended Audience :: Developers
Classifier: License :: OSI Approved :: BSD License
Classifier: Programming Language :: Python
Classifier: Programming Language :: Python :: 3
Classifier: Programming Language :: Python :: 3.13
Classifier: Topic :: Scientific/Engineering
Classifier: Topic :: Scientific/Engineering :: Artificial Intelligence
Requires-Python: >=3.13
Requires-Dist: numpy>=2.0.0
Requires-Dist: scipy>=1.15.0
Requires-Dist: scikit-learn>=1.4.0
Requires-Dist: pandas>=2.0.0
Dynamic: author
Dynamic: author-email
Dynamic: classifier
Dynamic: description
Dynamic: description-content-type
Dynamic: home-page
Dynamic: keywords
Dynamic: requires-dist
Dynamic: requires-python
Dynamic: summary
